fastapi_etag/__init__.py
fastapi_etag/dependency.py
fastapi_etag/example.py
fastapi_etag/py.typed
fastapi_etag/types.py
fastapi_etag-0.3.0.dist-info/WHEEL
fastapi_etag-0.3.0.dist-info/METADATA
fastapi_etag-0.3.0.dist-info/RECORD
