Metadata-Version: 2.1
Name: fastapi-etag
Version: 0.3.0
Summary: Convenience library for working with etags in fastapi
Home-page: https://github.com/steinitzu/fastapi-etag
License: MIT
Author: Steinthor Palsson
Author-email: steini90@gmail.com
Requires-Python: >=3.7,<4.0
Classifier: Environment :: Web Environment
Classifier: Intended Audience :: Developers
Classifier: License :: OSI Approved :: MIT License
Classifier: Programming Language :: Python :: 3
Classifier: Programming Language :: Python :: 3.7
Classifier: Programming Language :: Python :: 3.8
Classifier: Programming Language :: Python :: 3.9
Classifier: Topic :: Internet :: WWW/HTTP
Classifier: Topic :: Software Development :: Libraries :: Python Modules
Project-URL: Code, https://github.com/steinitzu/fastapi-etag
Project-URL: Issue tracker, https://github.com/steinitzu/fastapi-etag/issues
Project-URL: Repository, https://github.com/steinitzu/fastapi-etag.git
